youtube_title_parse/__init__.py
youtube_title_parse/core.py
youtube_title_parse/fallback_artist.py
youtube_title_parse/fallback_title.py
youtube_title_parse/parse.py
youtube_title_parse/plugins/__init__.py
youtube_title_parse/plugins/base.py
youtube_title_parse/plugins/common.py
youtube_title_parse/plugins/quoted_title.py
youtube_title_parse/plugins/remove_file_extensions.py
youtube_title_parse-1.0.0.dist-info/LICENSE
youtube_title_parse-1.0.0.dist-info/METADATA
youtube_title_parse-1.0.0.dist-info/WHEEL
youtube_title_parse-1.0.0.dist-info/entry_points.txt
youtube_title_parse-1.0.0.dist-info/top_level.txt
youtube_title_parse-1.0.0.dist-info/RECORD
