Metadata-Version: 2.1
Name: youtube_title_parse
Version: 1.0.0
Summary: Parse the title of a YouTube video to try and get artist & song name
Home-page: https://github.com/lttkgp/youtube-title-parse
Author: lttkgp
Author-email: ghostwriternr@gmail.com
License: MIT
Keywords: youtube,title,metadata,parse,music
Platform: UNKNOWN
Classifier: Development Status :: 5 - Production/Stable
Classifier: Intended Audience :: Developers
Classifier: License :: OSI Approved :: MIT License
Classifier: Natural Language :: English
Classifier: Programming Language :: Python :: 2.7
Classifier: Programming Language :: Python :: 3
